AUTHORS
COPYING
COPYING-PLAIN
MANIFEST.in
README
ez_setup.py
setup.cfg
setup.py
efl_utils/__init__.py
efl_utils/animations.py
efl_utils/callbacks.py
efl_utils/transitions.py
examples/01-transition_function.py
examples/02-transition_fade.py
examples/03-transition_slide.py
examples/04-animation_color.py
python_efl_utils.egg-info/PKG-INFO
python_efl_utils.egg-info/SOURCES.txt
python_efl_utils.egg-info/dependency_links.txt
python_efl_utils.egg-info/top_level.txt
python_efl_utils.egg-info/zip-safe
