Metadata-Version: 1.0
Name: python-efl-utils
Version: 0.1.0
Summary: Python utilities to EFL development
Home-page: http://www.enlightenment.org/
Author: Gustavo Sverzut Barbieri
Author-email: barbieri@gmail.com
License: BSD
Keywords: enlightenment graphics raster evas canvas utilities efl
Platform: UNKNOWN
Classifier: Development Status :: 3 - Alpha
Classifier: Environment :: Console :: Framebuffer
Classifier: Environment :: X11 Applications
Classifier: Intended Audience :: Developers
Classifier: License :: OSI Approved :: BSD License
Classifier: Operating System :: MacOS :: MacOS X
Classifier: Operating System :: POSIX
Classifier: Programming Language :: C
Classifier: Programming Language :: Python
Classifier: Topic :: Software Development :: Libraries :: Python Modules
Classifier: Topic :: Software Development :: User Interfaces
